jupyter_widget_stixview/__init__.py
jupyter_widget_stixview/_version.py
jupyter_widget_stixview/widget.py
jupyter_widget_stixview/static/extension.js
jupyter_widget_stixview/static/index.js
jupyter_widget_stixview/static/index.js.map
jupyter_widget_stixview-1.0.1.data/data/etc/jupyter/nbconfig/notebook.d/jupyter-widget-stixview.json
jupyter_widget_stixview-1.0.1.data/data/share/jupyter/nbextensions/jupyter-widget-stixview/extension.js
jupyter_widget_stixview-1.0.1.data/data/share/jupyter/nbextensions/jupyter-widget-stixview/index.js
jupyter_widget_stixview-1.0.1.data/data/share/jupyter/nbextensions/jupyter-widget-stixview/index.js.map
jupyter_widget_stixview-1.0.1.dist-info/LICENSE
jupyter_widget_stixview-1.0.1.dist-info/METADATA
jupyter_widget_stixview-1.0.1.dist-info/WHEEL
jupyter_widget_stixview-1.0.1.dist-info/top_level.txt
jupyter_widget_stixview-1.0.1.dist-info/RECORD
